ipfs_api/__init__.py
ipfs_cli/__init__.py
ipfs_datatransmission/__init__.py
ipfs_lns/__init__.py
ipfs_peers/__init__.py
ipfs_remote/__init__.py
ipfs_remote/client.py
ipfs_remote/files.py
ipfs_remote/ipns.py
ipfs_remote/peers.py
ipfs_remote/pubsub.py
ipfs_remote/tunnels.py
ipfs_remote/ipfshttpclient2/__init__.py
ipfs_remote/ipfshttpclient2/encoding.py
ipfs_remote/ipfshttpclient2/exceptions.py
ipfs_remote/ipfshttpclient2/filescanner.py
ipfs_remote/ipfshttpclient2/http.py
ipfs_remote/ipfshttpclient2/http_common.py
ipfs_remote/ipfshttpclient2/http_httpx.py
ipfs_remote/ipfshttpclient2/http_requests.py
ipfs_remote/ipfshttpclient2/multipart.py
ipfs_remote/ipfshttpclient2/requests_wrapper.py
ipfs_remote/ipfshttpclient2/utils.py
ipfs_remote/ipfshttpclient2/version.py
ipfs_remote/ipfshttpclient2/client/__init__.py
ipfs_remote/ipfshttpclient2/client/base.py
ipfs_remote/ipfshttpclient2/client/bitswap.py
ipfs_remote/ipfshttpclient2/client/block.py
ipfs_remote/ipfshttpclient2/client/bootstrap.py
ipfs_remote/ipfshttpclient2/client/config.py
ipfs_remote/ipfshttpclient2/client/dag.py
ipfs_remote/ipfshttpclient2/client/dht.py
ipfs_remote/ipfshttpclient2/client/files.py
ipfs_remote/ipfshttpclient2/client/key.py
ipfs_remote/ipfshttpclient2/client/miscellaneous.py
ipfs_remote/ipfshttpclient2/client/name.py
ipfs_remote/ipfshttpclient2/client/p2p.py
ipfs_remote/ipfshttpclient2/client/pin.py
ipfs_remote/ipfshttpclient2/client/pubsub.py
ipfs_remote/ipfshttpclient2/client/repo.py
ipfs_remote/ipfshttpclient2/client/routing.py
ipfs_remote/ipfshttpclient2/client/swarm.py
ipfs_remote/ipfshttpclient2/client/unstable.py
ipfs_tk/ipfs_tk_generics/__init__.py
ipfs_tk/ipfs_tk_generics/base_client.py
ipfs_tk/ipfs_tk_generics/client.py
ipfs_tk/ipfs_tk_generics/files.py
ipfs_tk/ipfs_tk_generics/ipns.py
ipfs_tk/ipfs_tk_generics/peers.py
ipfs_tk/ipfs_tk_generics/pubsub.py
ipfs_tk/ipfs_tk_generics/tunnels.py
ipfs_tk/ipfs_tk_peer_monitor/__init__.py
ipfs_tk/ipfs_tk_transmission/__init__.py
ipfs_toolkit-0.5.33.dist-info/METADATA
ipfs_toolkit-0.5.33.dist-info/WHEEL
ipfs_toolkit-0.5.33.dist-info/top_level.txt
ipfs_toolkit-0.5.33.dist-info/RECORD
