Metadata-Version: 2.4
Name: ipfs_toolkit
Version: 0.5.33
Summary: A set of tools  for working with IPFS in Python: a programmer-friendly API wrapper, P2P data-transmission machinery, and accelerated connections to known peers
Author: emendir
Project-URL: Homepage, https://ipfs.io/ipns/k2k4r8k7h909zdodsvbxe32sahpfdkqcqqn1npblummw4df6iv7dj5xh#IPFS-Toolkit
Project-URL: Github, https://github.com/emendir/IPFS-Toolkit-Python
Classifier: Programming Language :: Python :: 3
Classifier: Operating System :: OS Independent
Requires-Python: >=3.6
Requires-Dist: setuptools
Requires-Dist: wheel
Requires-Dist: appdirs
Requires-Dist: multiaddr
Requires-Dist: idna
Requires-Dist: httpx
Requires-Dist: requests
Requires-Dist: termcolor
Requires-Dist: cachetools
Requires-Dist: ipfs_tk
Requires-Dist: ipfs_node
